{
  "RocoDataRows": {
    "door_open_distance": {
      "id": 13,
      "key": "door_open_distance",
      "num": 200,
      "is_loc": 2
    },
    "door_close_time": {
      "id": 14,
      "key": "door_close_time",
      "num": 15000,
      "is_loc": 2
    },
    "home_furni_world_map_id": {
      "id": 20,
      "key": "home_furni_world_map_id",
      "num": 10003,
      "is_loc": 2
    },
    "enter_home_tips_show_time": {
      "id": 23,
      "key": "enter_home_tips_show_time",
      "num": 5,
      "is_loc": 2
    },
    "home_edit_FOV_initial": {
      "id": 24,
      "key": "home_edit_FOV_initial",
      "num": 80,
      "is_loc": 2
    },
    "home_edit_FOV_change_max": {
      "id": 25,
      "key": "home_edit_FOV_change_max",
      "num": 12000,
      "is_loc": 2
    },
    "home_edit_FOV_change_min": {
      "id": 26,
      "key": "home_edit_FOV_change_min",
      "num": 8000,
      "is_loc": 2
    },
    "furniture_num_max": {
      "id": 27,
      "key": "furniture_num_max",
      "num": 200,
      "is_loc": 2
    },
    "room_name_text_length": {
      "id": 28,
      "key": "room_name_text_length",
      "num": 12,
      "is_loc": 2
    },
    "home_reloading_auto_confirm_time": {
      "id": 29,
      "key": "home_reloading_auto_confirm_time",
      "num": 7,
      "is_loc": 2
    },
    "home_visitor_num_max": {
      "id": 30,
      "key": "home_visitor_num_max",
      "numList": [
        1,
        4,
        8
      ],
      "is_loc": 2
    },
    "home_not_approved_times": {
      "id": 31,
      "key": "home_not_approved_times",
      "num": 5,
      "is_loc": 2
    },
    "offline_visit_information_save_num": {
      "id": 32,
      "key": "offline_visit_information_save_num",
      "num": 50,
      "is_loc": 2
    },
    "offline_visit_information_save_time": {
      "id": 33,
      "key": "offline_visit_information_save_time",
      "num": 30,
      "is_loc": 2
    },
    "home_edit_guest_tips_showtime": {
      "id": 34,
      "key": "home_edit_guest_tips_showtime",
      "num": 10,
      "is_loc": 2
    },
    "Furniture_ding_number": {
      "id": 35,
      "key": "Furniture_ding_number",
      "num": 6,
      "is_loc": 2
    },
    "Funiture_ding_switch": {
      "id": 36,
      "key": "Funiture_ding_switch",
      "num": 1,
      "is_loc": 2
    },
    "Funiture_ding_refresh_time": {
      "id": 37,
      "key": "Funiture_ding_refresh_time",
      "num": 10080,
      "is_loc": 2
    },
    "Funiture_ding_Begin_time": {
      "id": 38,
      "key": "Funiture_ding_Begin_time",
      "numList": [
        0
      ],
      "str": "2025-05-09 04:00:00",
      "is_loc": 2
    },
    "home_house_flag_change_taskparagraph": {
      "id": 40,
      "key": "home_house_flag_change_taskparagraph",
      "num": 60115,
      "is_loc": 1
    },
    "room_name": {
      "id": 41,
      "key": "room_name",
      "str": "客厅;房间1;房间2;地下室;二楼房间",
      "is_loc": 1
    },
    "scene_magic_ban": {
      "id": 53,
      "key": "scene_magic_ban",
      "str": "SMT_CREATE;SMT_CREATE_MAGIC_MASSAGE",
      "is_loc": 2
    },
    "scene_magic_ban_plant": {
      "id": 54,
      "key": "scene_magic_ban_plant",
      "str": "SMT_CREATE;SMT_CREATE_MAGIC_MASSAGE",
      "is_loc": 2
    },
    "home_decoration_cd": {
      "id": 57,
      "key": "home_decoration_cd",
      "num": 10,
      "is_loc": 1
    },
    "online_visit_tag_retain_time": {
      "id": 58,
      "key": "online_visit_tag_retain_time",
      "num": 120,
      "is_loc": 2
    },
    "enter_home_from_friend_list": {
      "id": 59,
      "key": "enter_home_from_friend_list",
      "num": 1057,
      "is_loc": 2
    },
    "online_visit_home_enter_CD": {
      "id": 60,
      "key": "online_visit_home_enter_CD",
      "num": 5,
      "is_loc": 2
    },
    "invite_visit_home_break_team_show_time": {
      "id": 61,
      "key": "invite_visit_home_break_team_show_time",
      "num": 5,
      "is_loc": 2
    },
    "home_steal_reward_ratio": {
      "id": 101,
      "key": "home_steal_reward_ratio",
      "numList": [
        400,
        500,
        600,
        700,
        800
      ],
      "is_loc": 2
    },
    "home_daily_steal_reward_max": {
      "id": 102,
      "key": "home_daily_steal_reward_max",
      "num": 99999,
      "is_loc": 2
    },
    "home_pet_left_steal_max": {
      "id": 103,
      "key": "home_pet_left_steal_max",
      "num": 6000,
      "is_loc": 2
    },
    "home_reward_visible_distance": {
      "id": 104,
      "key": "home_reward_visible_distance",
      "num": 150,
      "is_loc": 2
    },
    "home_steal_attack_low": {
      "id": 105,
      "key": "home_steal_attack_low",
      "num": 1000,
      "numList": [
        0,
        30
      ],
      "is_loc": 2
    },
    "home_steal_attack_middle": {
      "id": 106,
      "key": "home_steal_attack_middle",
      "num": 1000,
      "numList": [
        30,
        60
      ],
      "is_loc": 2
    },
    "home_steal_attack_high": {
      "id": 107,
      "key": "home_steal_attack_high",
      "num": 1000,
      "numList": [
        60,
        100
      ],
      "is_loc": 2
    },
    "home_steal_attack_param": {
      "id": 108,
      "key": "home_steal_attack_param",
      "num": 1,
      "is_loc": 2
    },
    "home_pet_bed_icon_distance": {
      "id": 109,
      "key": "home_pet_bed_icon_distance",
      "num": 300,
      "is_loc": 2
    },
    "home_owner_visible_distance": {
      "id": 110,
      "key": "home_owner_visible_distance",
      "num": 300,
      "is_loc": 2
    },
    "home_highlight_visible_distance": {
      "id": 111,
      "key": "home_highlight_visible_distance",
      "num": 300,
      "is_loc": 2
    },
    "home_world_map_id": {
      "id": 112,
      "key": "home_world_map_id",
      "num": 10002,
      "is_loc": 2
    },
    "home_call_pet_radius": {
      "id": 113,
      "key": "home_call_pet_radius",
      "num": 5000,
      "is_loc": 2
    },
    "home_pet_feed_distance": {
      "id": 114,
      "key": "home_pet_feed_distance",
      "num": 1500,
      "is_loc": 2
    },
    "home_pet_feed_reward_distance": {
      "id": 115,
      "key": "home_pet_feed_reward_distance",
      "num": 1500,
      "is_loc": 2
    },
    "furniture_probability": {
      "id": 116,
      "key": "furniture_probability",
      "num": 5000,
      "is_loc": 2
    },
    "special_furniture_probability": {
      "id": 117,
      "key": "special_furniture_probability",
      "num": 5000,
      "is_loc": 2
    },
    "get_new_normal_furniture_times": {
      "id": 118,
      "key": "get_new_normal_furniture_times",
      "num": 6,
      "is_loc": 2
    },
    "emote_resource_path_m": {
      "id": 119,
      "key": "emote_resource_path_m",
      "str": "SkillBlueprint'/Game/ArtRes/Effects/G6Skill/Home/G6_Home_Call.G6_Home_Call'",
      "is_loc": 2
    },
    "emote_resource_path_w": {
      "id": 120,
      "key": "emote_resource_path_w",
      "str": "SkillBlueprint'/Game/ArtRes/Effects/G6Skill/Home/G6_Home_Call.G6_Home_Call'",
      "is_loc": 2
    },
    "call_resource_path": {
      "id": 121,
      "key": "call_resource_path",
      "str": "SkillBlueprint'/Game/ArtRes/Effects/G6Skill/Home/G6_Home_Call.G6_Home_Call'",
      "is_loc": 2
    },
    "home_steal_fix_value_friend": {
      "id": 122,
      "key": "home_steal_fix_value_friend",
      "is_loc": 2
    },
    "home_steal_fix_value_guest": {
      "id": 123,
      "key": "home_steal_fix_value_guest",
      "is_loc": 2
    },
    "get_furniture_cd": {
      "id": 124,
      "key": "get_furniture_cd",
      "num": 1,
      "is_loc": 2
    },
    "pet_steal_forbidding_time": {
      "id": 125,
      "key": "pet_steal_forbidding_time",
      "numList": [
        0,
        8
      ],
      "is_loc": 2
    },
    "home_pet_feed_mail_id": {
      "id": 126,
      "key": "home_pet_feed_mail_id",
      "num": 900006,
      "is_loc": 2
    },
    "home_feed_icon_visible_distance": {
      "id": 127,
      "key": "home_feed_icon_visible_distance",
      "num": 150,
      "is_loc": 2
    },
    "home_feed_resource_path": {
      "id": 128,
      "key": "home_feed_resource_path",
      "str": "happy;relax;show",
      "is_loc": 2
    },
    "home_steal_reward_resource_path": {
      "id": 129,
      "key": "home_steal_reward_resource_path",
      "str": "alert",
      "is_loc": 2
    },
    "home_petbed_camera_param": {
      "id": 130,
      "key": "home_petbed_camera_param",
      "numList": [
        30,
        300,
        0,
        0
      ],
      "is_loc": 2
    },
    "home_pet_feed_cd_distance": {
      "id": 131,
      "key": "home_pet_feed_cd_distance",
      "num": 150,
      "is_loc": 2
    },
    "home_pet_bed_none_distance": {
      "id": 132,
      "key": "home_pet_bed_none_distance",
      "num": 1500,
      "is_loc": 2
    },
    "plant_initial_coord": {
      "id": 201,
      "key": "plant_initial_coord",
      "num": 73010008,
      "is_loc": 2
    },
    "plant_length_side": {
      "id": 202,
      "key": "plant_length_side",
      "num": 160,
      "is_loc": 2
    },
    "plant_seed_bagitem_id": {
      "id": 203,
      "key": "plant_seed_bagitem_id",
      "num": 331000,
      "is_loc": 2
    },
    "plant_seed_harvestimg_path": {
      "id": 204,
      "key": "plant_seed_harvestimg_path",
      "str": "PaperSprite'/Game/NewRoco/Modules/System/Dialogue/Raw/Frames/img_Harvest_png.img_Harvest_png'",
      "is_loc": 2
    },
    "plant_coord_noticeboard": {
      "id": 205,
      "key": "plant_coord_noticeboard",
      "num": 701129,
      "is_loc": 2
    },
    "plant_coord_role_select_length": {
      "id": 206,
      "key": "plant_coord_role_select_length",
      "num": 160,
      "is_loc": 2
    },
    "plant_coord_role_select_high": {
      "id": 207,
      "key": "plant_coord_role_select_high",
      "num": 150,
      "is_loc": 2
    },
    "plant_coord_noticeboard_rotate": {
      "id": 208,
      "key": "plant_coord_noticeboard_rotate",
      "num": 73010005,
      "is_loc": 2
    },
    "plant_seed_rotate": {
      "id": 209,
      "key": "plant_seed_rotate",
      "num": 73010005,
      "is_loc": 2
    },
    "plant_steal_forbidding_time": {
      "id": 210,
      "key": "plant_steal_forbidding_time",
      "numList": [
        0,
        8
      ],
      "is_loc": 2
    },
    "plant_steal_same_plant_role_max": {
      "id": 211,
      "key": "plant_steal_same_plant_role_max",
      "num": 2,
      "is_loc": 2
    },
    "plant_rise_height": {
      "id": 212,
      "key": "plant_rise_height",
      "num": 30,
      "is_loc": 2
    },
    "plant_guard_pet_birth_point": {
      "id": 218,
      "key": "plant_guard_pet_birth_point",
      "num": 73010013,
      "is_loc": 2
    },
    "plant_steal_num_max": {
      "id": 219,
      "key": "plant_steal_num_max",
      "num": 120,
      "is_loc": 2
    },
    "plant_water_path": {
      "id": 220,
      "key": "plant_water_path",
      "str": "PaperSprite'/Game/NewRoco/Modules/System/MainUI/Raw/Atlas/MainUIStatic/Frames/img_HomePlanting_Watering_png.img_HomePlanting_Watering_png'",
      "is_loc": 2
    },
    "plant_manure_path": {
      "id": 221,
      "key": "plant_manure_path",
      "str": "PaperSprite'/Game/NewRoco/Modules/System/MainUI/Raw/Atlas/MainUIStatic/Frames/img_HomePlanting_Fertilization_png.img_HomePlanting_Fertilization_png'",
      "is_loc": 2
    },
    "plant_get_path": {
      "id": 222,
      "key": "plant_get_path",
      "str": "PaperSprite'/Game/NewRoco/Modules/System/MainUI/Raw/Atlas/MainUIStatic/Frames/img_HomePlanting_Harvestable2_png.img_HomePlanting_Harvestable2_png'",
      "is_loc": 2
    },
    "plant_guard_pet_birth_num": {
      "id": 223,
      "key": "plant_guard_pet_birth_num",
      "num": 1,
      "is_loc": 2
    },
    "plant_coord_noticeboard_head_icon": {
      "id": 224,
      "key": "plant_coord_noticeboard_head_icon",
      "str": "PaperSprite'/Game/NewRoco/Modules/System/MainUI/Raw/Atlas/Lobby/Frames/img_Cultivable_png.img_Cultivable_png'",
      "is_loc": 2
    },
    "plant_pet_water_distance": {
      "id": 225,
      "key": "plant_pet_water_distance",
      "num": 8000,
      "is_loc": 2
    },
    "plant_pet_manure_distance": {
      "id": 226,
      "key": "plant_pet_manure_distance",
      "num": 8000,
      "is_loc": 2
    },
    "plant_pet_pick_distance": {
      "id": 227,
      "key": "plant_pet_pick_distance",
      "num": 8000,
      "is_loc": 2
    },
    "home_check_in_spawn_offset_z": {
      "id": 228,
      "key": "home_check_in_spawn_offset_z",
      "num": 60,
      "is_loc": 2
    },
    "home_initiative_behavior_probabilities": {
      "id": 229,
      "key": "home_initiative_behavior_probabilities",
      "numList": [
        0,
        50,
        50
      ],
      "is_loc": 2
    },
    "home_pet_init_hallway_pos": {
      "id": 230,
      "key": "home_pet_init_hallway_pos",
      "numList": [
        -11,
        1373,
        0
      ],
      "is_loc": 2
    },
    "home_plant_chat_multi_interflow": {
      "id": 231,
      "key": "home_plant_chat_multi_interflow",
      "is_loc": 2
    },
    "home_room_expand_select": {
      "id": 232,
      "key": "home_room_expand_select",
      "numList": [
        131002,
        131006
      ],
      "is_loc": 2
    },
    "home_visit_level": {
      "id": 233,
      "key": "home_visit_level",
      "num": 3,
      "is_loc": 2
    },
    "home_bigworld_level_0": {
      "id": 234,
      "key": "home_bigworld_level_0",
      "str": "Plot_Homeworld_DerelictHouse",
      "is_loc": 2
    },
    "home_bigworld_level_1": {
      "id": 235,
      "key": "home_bigworld_level_1",
      "str": "Plot_Homeworld_House_01",
      "is_loc": 2
    },
    "home_bigworld_level_2": {
      "id": 236,
      "key": "home_bigworld_level_2",
      "str": "Plot_Homeworld_House_02",
      "is_loc": 2
    },
    "home_bigworld_level_3": {
      "id": 237,
      "key": "home_bigworld_level_3",
      "str": "Plot_Homeworld_House_03",
      "is_loc": 2
    },
    "home_bigworld_level_4": {
      "id": 238,
      "key": "home_bigworld_level_4",
      "str": "Plot_Homeworld_House_04",
      "is_loc": 2
    },
    "home_bigworld_level_5": {
      "id": 239,
      "key": "home_bigworld_level_5",
      "str": "Plot_Homeworld_House_05",
      "is_loc": 2
    },
    "home_visit_cd": {
      "id": 240,
      "key": "home_visit_cd",
      "num": 1,
      "is_loc": 2
    },
    "home_plant_sell_press": {
      "id": 241,
      "key": "home_plant_sell_press",
      "numList": [
        1500,
        10
      ],
      "is_loc": 2
    },
    "home_plant_sell_press_start": {
      "id": 242,
      "key": "home_plant_sell_press_start",
      "num": 3000,
      "is_loc": 2
    },
    "HOME_EDITTING_SHOW_NPCS": {
      "id": 243,
      "key": "HOME_EDITTING_SHOW_NPCS",
      "numList": [
        702001,
        520197,
        520251,
        520199,
        702002,
        520195,
        520193
      ],
      "is_loc": 2
    },
    "home_layout_release_CD": {
      "id": 244,
      "key": "home_layout_release_CD",
      "num": 30,
      "is_loc": 2
    },
    "home_visit_reload_time": {
      "id": 245,
      "key": "home_visit_reload_time",
      "num": 210,
      "is_loc": 2
    },
    "plant_empty_plant": {
      "id": 301,
      "key": "plant_empty_plant",
      "num": 701128,
      "is_loc": 2
    },
    "enter_plant_from_friend_list": {
      "id": 302,
      "key": "enter_plant_from_friend_list",
      "num": 1072,
      "is_loc": 2
    },
    "home_main_UI": {
      "id": 303,
      "key": "home_main_UI",
      "str": "FE_PET;FE_TASK;FE_EDIT_HOME;FE_FURNITURE_HANDBOOK",
      "is_loc": 2
    },
    "visit_home_main_UI": {
      "id": 304,
      "key": "visit_home_main_UI",
      "str": "FE_PET;FE_TASK;FE_FURNITURE_HANDBOOK",
      "is_loc": 2
    },
    "plant_main_UI": {
      "id": 305,
      "key": "plant_main_UI",
      "str": "FE_PET;FE_TASK;FE_FURNITURE_HANDBOOK",
      "is_loc": 2
    },
    "plant_guard_pet_random_point": {
      "id": 306,
      "key": "plant_guard_pet_random_point",
      "num": 73010029,
      "is_loc": 2
    },
    "home_plant_steal_attack_low": {
      "id": 307,
      "key": "home_plant_steal_attack_low",
      "num": 10000,
      "is_loc": 2
    },
    "home_plant_steal_attack_middle": {
      "id": 308,
      "key": "home_plant_steal_attack_middle",
      "num": 10000,
      "is_loc": 2
    },
    "home_plant_steal_attack_high": {
      "id": 309,
      "key": "home_plant_steal_attack_high",
      "num": 10000,
      "is_loc": 2
    },
    "home_plant_steal_attack_CD": {
      "id": 310,
      "key": "home_plant_steal_attack_CD",
      "num": 1800,
      "is_loc": 2
    },
    "plant_water_tips_height_born": {
      "id": 311,
      "key": "plant_water_tips_height_born",
      "num": 255,
      "is_loc": 2
    },
    "plant_water_no_tips_dist": {
      "id": 312,
      "key": "plant_water_no_tips_dist",
      "num": 2000,
      "is_loc": 2
    },
    "furniture_handbook_friendinformation_num": {
      "id": 313,
      "key": "furniture_handbook_friendinformation_num",
      "num": 50,
      "is_loc": 2
    },
    "invite_home_owner_timeout": {
      "id": 314,
      "key": "invite_home_owner_timeout",
      "num": 1800,
      "is_loc": 2
    },
    "furniture_craftable_friend_list_pagination_threshold": {
      "id": 315,
      "key": "furniture_craftable_friend_list_pagination_threshold",
      "num": 500,
      "is_loc": 2
    }
  },
  "LocalizationStrings": {}
}